{"ResultsReport": {"ResultsPayload": {"FinalReport": {"Sample": {"FM_Id": null, "SampleId": null, "BlockId": "S110-75737A", "TRFNumber": null, "TestType": "Oncomine Focus Assay", "SpecFormat": "FFPE", "ReceivedDate": null, "TumorPurity": "40", "SpecimenLocation": "nan"}, "PMI": {"ReportId": "S110-98404", "MRN": "32552991", "FullName": "\u5433\u6842\u947e", "FirstName": null, "LastName": null, "SubmittedDiagnosis": "Metastatic carcinoma", "Gender": "Female", "DOB": null, "OrderingMD": "\u7f85\u6c38\u9d3b", "OrderingMDId": "DOC8784G", "Pathologist": "\u8449\u5955\u6210", "CopiedPhysician1": null, "MedFacilName": null, "MedFacilID": null, "SpecSite": null, "CollDate": null, "ReceivedDate": "2021-03-19 00:00:00", "CountryOfOrigin": null, "TumorType": "Non-Small Cell Lung Cancer"}}, "variant_report": {"short_variants": null, "copy_number_alterations": {"copy_number_alteration": [{"copy_number": "9.05", "gene": "EGFR", "position": "chr7:55198956"}, {"copy_number": "78.43", "gene": "ERBB2", "position": "chr17:37868126"}]}, "rearrangements": null, "biomarkers": {"microsatellite_instability": {"status": null}, "tumor_mutation_burden": {"score": null}}}}}}