{"ResultsReport": {"ResultsPayload": {"FinalReport": {"Sample": {"FM_Id": null, "SampleId": null, "BlockId": "S110-19377B", "TRFNumber": null, "TestType": "ACTOnco", "SpecFormat": "FFPE", "ReceivedDate": "Oct 05, 2021", "TumorPurity": "73", "SpecimenLocation": "nan"}, "PMI": {"ReportId": "S110-99812", "MRN": "44003761", "FullName": "\u9673\u4fe1\u745c", "FirstName": null, "LastName": null, "SubmittedDiagnosis": "Metastatic ewing sarcoma, Lung", "Gender": "Male", "DOB": "Sep 15, 1994", "OrderingMD": "\u5f90\u535a\u594e", "OrderingMDId": null, "Pathologist": "\u676d\u4ec1\u91e9", "CopiedPhysician1": null, "MedFacilName": null, "MedFacilID": null, "SpecSite": "Lung", "CollDate": null, "ReceivedDate": "2021-10-21 00:00:00", "CountryOfOrigin": null, "TumorType": "Sarcoma"}}, "variant_report": {"short_variants": null, "copy_number_alterations": {"copy_number_alteration": [{"copy_number": "ND", "gene": "ND", "position": "ND", "type": "Amplification"}, {"copy_number": "0", "gene": "ND", "position": "ND", "type": "Homozygous deletion"}, {"copy_number": "1", "gene": "ND", "position": "ND", "type": "Heterozygous deletion"}, {"copy_number": "1", "gene": "Detected", "position": "ND,Not", "type": "Heterozygous deletion"}]}, "rearrangements": null, "biomarkers": {"microsatellite_instability": {"status": null}, "tumor_mutation_burden": {"score": null}}}}}}