{"ResultsReport": {"ResultsPayload": {"FinalReport": {"Sample": {"FM_Id": null, "SampleId": null, "BlockId": "nan", "TRFNumber": null, "TestType": "Oncomine Myeloid Assay", "SpecFormat": "Bone Marrow", "ReceivedDate": "2022/06/30", "TumorPurity": "nan", "SpecimenLocation": "nan"}, "PMI": {"ReportId": "S111-99724", "MRN": "15770828", "FullName": "\u5b98\u5b9c\u6f54", "FirstName": null, "LastName": null, "SubmittedDiagnosis": "Other Hematological Cancer", "Gender": "Female", "DOB": null, "OrderingMD": "\u67ef\u535a\u4f38", "OrderingMDId": "DOC4205A", "Pathologist": "\u8449\u5955\u6210", "CopiedPhysician1": null, "MedFacilName": null, "MedFacilID": null, "SpecSite": null, "CollDate": null, "ReceivedDate": "2022-07-08 00:00:00", "CountryOfOrigin": null, "TumorType": "Other Hematological Cancer"}}, "variant_report": {"short_variants": null, "copy_number_alterations": null, "rearrangements": null, "biomarkers": {"microsatellite_instability": {"status": null}, "tumor_mutation_burden": {"score": null}}}}}}